topsis_102383046/__init__.py
topsis_102383046/cli.py
topsis_102383046/topsis.py
102383046_topsis-0.6.dist-info/METADATA
102383046_topsis-0.6.dist-info/WHEEL
102383046_topsis-0.6.dist-info/entry_points.txt
102383046_topsis-0.6.dist-info/top_level.txt
102383046_topsis-0.6.dist-info/RECORD
