Metadata-Version: 2.1
Name: 102383046-topsis
Version: 0.6
Summary: TOPSIS implementation for best decision-making  
Author: Navkaran Singh Randhawa
Author-email: manveerrandhawa0055@gmail.com
Classifier: Programming Language :: Python :: 3
Classifier: License :: OSI Approved :: MIT License
Classifier: Operating System :: OS Independent
